CHANGES.rst
LICENSE
MANIFEST.in
README.rst
asl.py
requirements.txt
setup.py
pygments_asl.egg-info/PKG-INFO
pygments_asl.egg-info/SOURCES.txt
pygments_asl.egg-info/dependency_links.txt
pygments_asl.egg-info/entry_points.txt
pygments_asl.egg-info/requires.txt
pygments_asl.egg-info/top_level.txt
pygments_asl.egg-info/zip-safe