Metadata-Version: 1.1
Name: pygments-asl
Version: 1.0
Summary: Pygments lexer for ACPI source language (ASL)
Home-page: http://pypi.python.org/pypi/pygments-asl
Author: Aron Curzon
Author-email: curzona@gmail.com
License: BSD
Keywords: pygments acpi asl aml
Platform: UNKNOWN
Classifier: Development Status :: 3 - Alpha
Classifier: Environment :: Plugins
Classifier: Intended Audience :: Developers
Classifier: License :: OSI Approved :: BSD License
Classifier: Operating System :: OS Independent
Classifier: Programming Language :: Python :: 2
